{
  "id": "39e283df-0c06-4b6a-a65c-2d3591834181",
  "prevId": "00000000-0000-0000-0000-000000000000",
  "version": "7",
  "dialect": "postgresql",
  "tables": {
    "public.day_logs": {
      "name": "day_logs",
      "schema": "",
      "columns": {
        "id": {
          "name": "id",
          "type": "serial",
          "primaryKey": true,
          "notNull": true
        },
        "date": {
          "name": "date",
          "type": "date",
          "primaryKey": false,
          "notNull": true
        },
        "feel": {
          "name": "feel",
          "type": "integer",
          "primaryKey": false,
          "notNull": false
        },
        "comment": {
          "name": "comment",
          "type": "text",
          "primaryKey": false,
          "notNull": false
        },
        "updated_at": {
          "name": "updated_at",
          "type": "timestamp with time zone",
          "primaryKey": false,
          "notNull": true,
          "default": "now()"
        }
      },
      "indexes": {},
      "foreignKeys": {},
      "compositePrimaryKeys": {},
      "uniqueConstraints": {
        "day_logs_date_unique": {
          "name": "day_logs_date_unique",
          "nullsNotDistinct": false,
          "columns": [
            "date"
          ]
        }
      },
      "policies": {},
      "checkConstraints": {},
      "isRLSEnabled": false
    },
    "public.exercise_logs": {
      "name": "exercise_logs",
      "schema": "",
      "columns": {
        "id": {
          "name": "id",
          "type": "serial",
          "primaryKey": true,
          "notNull": true
        },
        "plan_exercise_id": {
          "name": "plan_exercise_id",
          "type": "integer",
          "primaryKey": false,
          "notNull": false
        },
        "date": {
          "name": "date",
          "type": "date",
          "primaryKey": false,
          "notNull": true
        },
        "exercise_name": {
          "name": "exercise_name",
          "type": "text",
          "primaryKey": false,
          "notNull": true
        },
        "actual": {
          "name": "actual",
          "type": "text",
          "primaryKey": false,
          "notNull": false
        },
        "comment": {
          "name": "comment",
          "type": "text",
          "primaryKey": false,
          "notNull": false
        },
        "done": {
          "name": "done",
          "type": "boolean",
          "primaryKey": false,
          "notNull": true,
          "default": false
        },
        "updated_at": {
          "name": "updated_at",
          "type": "timestamp with time zone",
          "primaryKey": false,
          "notNull": true,
          "default": "now()"
        }
      },
      "indexes": {},
      "foreignKeys": {
        "exercise_logs_plan_exercise_id_plan_exercises_id_fk": {
          "name": "exercise_logs_plan_exercise_id_plan_exercises_id_fk",
          "tableFrom": "exercise_logs",
          "tableTo": "plan_exercises",
          "columnsFrom": [
            "plan_exercise_id"
          ],
          "columnsTo": [
            "id"
          ],
          "onDelete": "set null",
          "onUpdate": "no action"
        }
      },
      "compositePrimaryKeys": {},
      "uniqueConstraints": {
        "exercise_logs_plan_exercise_id_unique": {
          "name": "exercise_logs_plan_exercise_id_unique",
          "nullsNotDistinct": false,
          "columns": [
            "plan_exercise_id"
          ]
        }
      },
      "policies": {},
      "checkConstraints": {},
      "isRLSEnabled": false
    },
    "public.plan_days": {
      "name": "plan_days",
      "schema": "",
      "columns": {
        "id": {
          "name": "id",
          "type": "serial",
          "primaryKey": true,
          "notNull": true
        },
        "date": {
          "name": "date",
          "type": "date",
          "primaryKey": false,
          "notNull": true
        },
        "day_of_week": {
          "name": "day_of_week",
          "type": "text",
          "primaryKey": false,
          "notNull": false
        },
        "week_label": {
          "name": "week_label",
          "type": "text",
          "primaryKey": false,
          "notNull": false
        },
        "month_label": {
          "name": "month_label",
          "type": "text",
          "primaryKey": false,
          "notNull": false
        },
        "workout_type": {
          "name": "workout_type",
          "type": "text",
          "primaryKey": false,
          "notNull": false
        },
        "focus": {
          "name": "focus",
          "type": "text",
          "primaryKey": false,
          "notNull": false
        },
        "planned_raw": {
          "name": "planned_raw",
          "type": "text",
          "primaryKey": false,
          "notNull": false
        },
        "target_notes": {
          "name": "target_notes",
          "type": "text",
          "primaryKey": false,
          "notNull": false
        },
        "position": {
          "name": "position",
          "type": "integer",
          "primaryKey": false,
          "notNull": true,
          "default": 0
        }
      },
      "indexes": {},
      "foreignKeys": {},
      "compositePrimaryKeys": {},
      "uniqueConstraints": {
        "plan_days_date_unique": {
          "name": "plan_days_date_unique",
          "nullsNotDistinct": false,
          "columns": [
            "date"
          ]
        }
      },
      "policies": {},
      "checkConstraints": {},
      "isRLSEnabled": false
    },
    "public.plan_exercises": {
      "name": "plan_exercises",
      "schema": "",
      "columns": {
        "id": {
          "name": "id",
          "type": "serial",
          "primaryKey": true,
          "notNull": true
        },
        "plan_day_id": {
          "name": "plan_day_id",
          "type": "integer",
          "primaryKey": false,
          "notNull": true
        },
        "position": {
          "name": "position",
          "type": "integer",
          "primaryKey": false,
          "notNull": true
        },
        "name": {
          "name": "name",
          "type": "text",
          "primaryKey": false,
          "notNull": true
        },
        "target": {
          "name": "target",
          "type": "text",
          "primaryKey": false,
          "notNull": false
        },
        "raw": {
          "name": "raw",
          "type": "text",
          "primaryKey": false,
          "notNull": false
        }
      },
      "indexes": {},
      "foreignKeys": {
        "plan_exercises_plan_day_id_plan_days_id_fk": {
          "name": "plan_exercises_plan_day_id_plan_days_id_fk",
          "tableFrom": "plan_exercises",
          "tableTo": "plan_days",
          "columnsFrom": [
            "plan_day_id"
          ],
          "columnsTo": [
            "id"
          ],
          "onDelete": "cascade",
          "onUpdate": "no action"
        }
      },
      "compositePrimaryKeys": {},
      "uniqueConstraints": {
        "plan_exercises_day_position": {
          "name": "plan_exercises_day_position",
          "nullsNotDistinct": false,
          "columns": [
            "plan_day_id",
            "position"
          ]
        }
      },
      "policies": {},
      "checkConstraints": {},
      "isRLSEnabled": false
    }
  },
  "enums": {},
  "schemas": {},
  "sequences": {},
  "roles": {},
  "policies": {},
  "views": {},
  "_meta": {
    "columns": {},
    "schemas": {},
    "tables": {}
  }
}